Workbook

Sheet Clientes
B1: Clientes de empréstimos
A5: ID_Cliente | B5: Nome | C5: Valor | D5: Data | E5: Juros | F5: Multa por atraso a.d | G5: Vencimento | H5: Dia pagamento | I5: Dias para quitação | J5: Dias de atraso | K5: Parcelas | L5: Parcelas faltantes | M5: Valor parcela | N5: Total | O5: Status | P5: Juros totais | Q5: Valor Faltante
A6: 1 | B6: =VLOOKUP(Tabela2[[#This Row],[ID_Cliente]],Tabela5[#All],2,0) -> Armando rodrigues progenio neto | C6: 53.5 | D6: 45689 | E6: =SUM(Encargos!$A$5/12,Encargos!$C$5,Encargos!$E$5) -> 0.0325 | F6: {=Tabela1[Multa por atraso]} -> 0.01 | G6: 45694 | H6: 45696 | I6: 5 | J6: =IF(TODAY()-G6<0,"No prazo",IF(Tabela2[[#This Row],[Status]]="Pago",Tabela2[[#This Row],[Dia pagamento]]-Tabela2[[#This Row],[Vencimento]],TODAY()-G6)) -> 2 | K6: 1 | L6: 1 | M6: {=(C6+(C6*(E6*Tabela2[[#This Row],[Parcelas]]))+(C6*(Tabela1[I.O.F Diário]*Clientes!I6)))/K6+IF(TODAY()>G6,(C6*(F6*J6)),0)} -> 56.330685 | N6: =M6*K6 -> 56.330685 | O6: Pago | P6: =Tabela2[[#This Row],[Total]]-Tabela2[[#This Row],[Valor]] -> 2.830685 | Q6: =Tabela2[[#This Row],[Valor parcela]]*Tabela2[[#This Row],[Parcelas faltantes]] -> 56.330685
A7: 1 | B7: =VLOOKUP(Tabela2[[#This Row],[ID_Cliente]],Tabela5[#All],2,0) -> Armando rodrigues progenio neto | C7: 54.78 | D7: 45696 | E7: =SUM(Encargos!$A$5/12,Encargos!$C$5,Encargos!$E$5) -> 0.0325 | F7: {=Tabela1[Multa por atraso]} -> 0.01 | G7: 45708 | H7: 45708 | I7: 12 | J7: =IF(TODAY()-G7<0,"No prazo",IF(Tabela2[[#This Row],[Status]]="Pago",Tabela2[[#This Row],[Dia pagamento]]-Tabela2[[#This Row],[Vencimento]],TODAY()-G7)) -> 0 | K7: 1 | L7: 1 | M7: {=(C7+(C7*(E7*Tabela2[[#This Row],[Parcelas]]))+(C7*(Tabela1[I.O.F Diário]*Clientes!I7)))/K7+IF(TODAY()>G7,(C7*(F7*J7)),0)} -> 56.614254 | N7: =M7*K7 -> 56.614254 | O7: Pago | P7: =Tabela2[[#This Row],[Total]]-Tabela2[[#This Row],[Valor]] -> 1.8342535 | Q7: =Tabela2[[#This Row],[Valor parcela]]*Tabela2[[#This Row],[Parcelas faltantes]] -> 56.614254
A8: 1 | B8: =VLOOKUP(Tabela2[[#This Row],[ID_Cliente]],Tabela5[#All],2,0) -> Armando rodrigues progenio neto | C8: 87.49 | D8: 45717 | E8: =SUM(Encargos!$A$5/12,Encargos!$C$5,Encargos!$E$5) -> 0.0325 | F8: {=Tabela1[Multa por atraso]} -> 0.01 | G8: 45722 | H8: 45722 | I8: 5 | J8: =IF(TODAY()-G8<0,"No prazo",IF(Tabela2[[#This Row],[Status]]="Pago",Tabela2[[#This Row],[Dia pagamento]]-Tabela2[[#This Row],[Vencimento]],TODAY()-G8)) -> 0 | K8: 1 | L8: 1 | M8: {=(C8+(C8*(E8*Tabela2[[#This Row],[Parcelas]]))+(C8*(Tabela1[I.O.F Diário]*Clientes!I8)))/K8+IF(TODAY()>G8,(C8*(F8*J8)),0)} -> 90.369296 | N8: =M8*K8 -> 90.369296 | O8: Pago | P8: =Tabela2[[#This Row],[Total]]-Tabela2[[#This Row],[Valor]] -> 2.8792959 | Q8: =Tabela2[[#This Row],[Valor parcela]]*Tabela2[[#This Row],[Parcelas faltantes]] -> 90.369296
A9: 1 | B9: =VLOOKUP(Tabela2[[#This Row],[ID_Cliente]],Tabela5[#All],2,0) -> Armando rodrigues progenio neto | C9: 9.75 | D9: 45724 | E9: =SUM(Encargos!$A$5/12,Encargos!$C$5,Encargos!$E$5) -> 0.0325 | F9: {=Tabela1[Multa por atraso]} -> 0.01 | G9: 45736 | H9: 45730 | I9: 12 | J9: =IF(TODAY()-G9<0,"No prazo",IF(Tabela2[[#This Row],[Status]]="Pago",Tabela2[[#This Row],[Dia pagamento]]-Tabela2[[#This Row],[Vencimento]],TODAY()-G9)) -> -6 | K9: 1 | L9: 1 | M9: {=(C9+(C9*(E9*Tabela2[[#This Row],[Parcelas]]))+(C9*(Tabela1[I.O.F Diário]*Clientes!I9)))/K9+IF(TODAY()>G9,(C9*(F9*J9)),0)} -> 9.491469 | N9: =M9*K9 -> 9.491469 | O9: Pago | P9: =Tabela2[[#This Row],[Total]]-Tabela2[[#This Row],[Valor]] -> -0.258531 | Q9: =Tabela2[[#This Row],[Valor parcela]]*Tabela2[[#This Row],[Parcelas faltantes]] -> 9.491469
A10: 1 | B10: =VLOOKUP(Tabela2[[#This Row],[ID_Cliente]],Tabela5[#All],2,0) -> Armando rodrigues progenio neto | C10: 93 | D10: 45733 | E10: =SUM(Encargos!$A$5/12,Encargos!$C$5,Encargos!$E$5) -> 0.0325 | F10: {=Tabela1[Multa por atraso]} -> 0.01 | G10: 45736 | H10: 45736 | I10: 3 | J10: =IF(TODAY()-G10<0,"No prazo",IF(Tabela2[[#This Row],[Status]]="Pago",Tabela2[[#This Row],[Dia pagamento]]-Tabela2[[#This Row],[Vencimento]],TODAY()-G10)) -> 0 | K10: 1 | L10: 1 | M10: {=(C10+(C10*(E10*Tabela2[[#This Row],[Parcelas]]))+(C10*(Tabela1[I.O.F Diário]*Clientes!I10)))/K10+IF(TODAY()>G10,(C10*(F10*J10)),0)} -> 96.045378 | N10: =M10*K10 -> 96.045378 | O10: Pago | P10: =Tabela2[[#This Row],[Total]]-Tabela2[[#This Row],[Valor]] -> 3.045378 | Q10: =Tabela2[[#This Row],[Valor parcela]]*Tabela2[[#This Row],[Parcelas faltantes]] -> 96.045378
A11: 1 | B11: =VLOOKUP(Tabela2[[#This Row],[ID_Cliente]],Tabela5[#All],2,0) -> Armando rodrigues progenio neto | C11: 224.02 | D11: 45744 | E11: =SUM(Encargos!$A$5/12,Encargos!$C$5,Encargos!$E$5) -> 0.0325 | F11: {=Tabela1[Multa por atraso]} -> 0.01 | G11: 45753 | H11: 45751 | I11: 9 | J11: =IF(TODAY()-G11<0,"No prazo",IF(Tabela2[[#This Row],[Status]]="Pago",Tabela2[[#This Row],[Dia pagamento]]-Tabela2[[#This Row],[Vencimento]],TODAY()-G11)) -> -2 | K11: 1 | L11: 1 | M11: {=(C11+(C11*(E11*Tabela2[[#This Row],[Parcelas]]))+(C11*(Tabela1[I.O.F Diário]*Clientes!I11)))/K11+IF(TODAY()>G11,(C11*(F11*J11)),0)} -> 226.98558 | N11: =M11*K11 -> 226.98558 | O11: Pago | P11: =Tabela2[[#This Row],[Total]]-Tabela2[[#This Row],[Valor]] -> 2.9655768 | Q11: =Tabela2[[#This Row],[Valor parcela]]*Tabela2[[#This Row],[Parcelas faltantes]] -> 226.98558
A12: 1 | B12: =VLOOKUP(Tabela2[[#This Row],[ID_Cliente]],Tabela5[#All],2,0) -> Armando rodrigues progenio neto | C12: 309.28 | D12: 45752 | E12: =SUM(Encargos!$A$5/12,Encargos!$C$5,Encargos!$E$5) -> 0.0325 | F12: {=Tabela1[Multa por atraso]} -> 0.01 | G12: 45767 | H12: 45765 | I12: 15 | J12: =IF(TODAY()-G12<0,"No prazo",IF(Tabela2[[#This Row],[Status]]="Pago",Tabela2[[#This Row],[Dia pagamento]]-Tabela2[[#This Row],[Vencimento]],TODAY()-G12)) -> -2 | K12: 1 | L12: 1 | M12: {=(C12+(C12*(E12*Tabela2[[#This Row],[Parcelas]]))+(C12*(Tabela1[I.O.F Diário]*Clientes!I12)))/K12+IF(TODAY()>G12,(C12*(F12*J12)),0)} -> 313.52641 | N12: =M12*K12 -> 313.52641 | O12: Pago | P12: =Tabela2[[#This Row],[Total]]-Tabela2[[#This Row],[Valor]] -> 4.2464144 | Q12: =Tabela2[[#This Row],[Valor parcela]]*Tabela2[[#This Row],[Parcelas faltantes]] -> 313.52641
A13: 1 | B13: =VLOOKUP(Tabela2[[#This Row],[ID_Cliente]],Tabela5[#All],2,0) -> Armando rodrigues progenio neto | C13: 347.6 | D13: 45765 | E13: =SUM(Encargos!$A$5/12,Encargos!$C$5,Encargos!$E$5) -> 0.0325 | F13: {=Tabela1[Multa por atraso]} -> 0.01 | G13: 45783 | H13: 45776 | I13: 18 | J13: =IF(TODAY()-G13<0,"No prazo",IF(Tabela2[[#This Row],[Status]]="Pago",Tabela2[[#This Row],[Dia pagamento]]-Tabela2[[#This Row],[Vencimento]],TODAY()-G13)) -> -7 | K13: 1 | L13: 1 | M13: {=(C13+(C13*(E13*Tabela2[[#This Row],[Parcelas]]))+(C13*(Tabela1[I.O.F Diário]*Clientes!I13)))/K13+IF(TODAY()>G13,(C13*(F13*J13)),0)} -> 335.07806 | N13: =M13*K13 -> 335.07806 | O13: Pago | P13: =Tabela2[[#This Row],[Total]]-Tabela2[[#This Row],[Valor]] -> -12.521942 | Q13: =Tabela2[[#This Row],[Valor parcela]]*Tabela2[[#This Row],[Parcelas faltantes]] -> 335.07806
A14: 1 | B14: =VLOOKUP(Tabela2[[#This Row],[ID_Cliente]],Tabela5[#All],2,0) -> Armando rodrigues progenio neto | C14: 492.06 | D14: 45776 | E14: =SUM(Encargos!$A$5/12,Encargos!$C$5,Encargos!$E$5) -> 0.0325 | F14: {=Tabela1[Multa por atraso]} -> 0.01 | G14: 45814 | H14: 45794 | I14: 38 | J14: =IF(TODAY()-G14<0,"No prazo",IF(Tabela2[[#This Row],[Status]]="Pago",Tabela2[[#This Row],[Dia pagamento]]-Tabela2[[#This Row],[Vencimento]],TODAY()-G14)) -> -20 | K14: 2 | L14: 1 | M14: {=(C14+(C14*(E14*Tabela2[[#This Row],[Parcelas]]))+(C14*(Tabela1[I.O.F Diário]*Clientes!I14)))/K14+IF(TODAY()>G14,(C14*(F14*J14)),0)} -> 164.37658 | N14: =M14*K14 -> 328.75316 | O14: Pago | P14: =Tabela2[[#This Row],[Total]]-Tabela2[[#This Row],[Valor]] -> -163.30684 | Q14: =Tabela2[[#This Row],[Valor parcela]]*Tabela2[[#This Row],[Parcelas faltantes]] -> 164.37658
A15: 1 | B15: =VLOOKUP(Tabela2[[#This Row],[ID_Cliente]],Tabela5[#All],2,0) -> Armando rodrigues progenio neto | C15: 485.27 | D15: 45794 | E15: =SUM(Encargos!$A$5/12,Encargos!$C$5,Encargos!$E$5) -> 0.0325 | F15: {=Tabela1[Multa por atraso]} -> 0.01 | G15: 45844 | H15: 45805 | I15: 52 | J15: =IF(TODAY()-G15<0,"No prazo",IF(Tabela2[[#This Row],[Status]]="Pago",Tabela2[[#This Row],[Dia pagamento]]-Tabela2[[#This Row],[Vencimento]],TODAY()-G15)) -> -39 | K15: 2 | L15: 1 | M15: {=(C15+(C15*(E15*Tabela2[[#This Row],[Parcelas]]))+(C15*(Tabela1[I.O.F Diário]*Clientes!I15)))/K15+IF(TODAY()>G15,(C15*(F15*J15)),0)} -> 70.185571 | N15: =M15*K15 -> 140.37114 | O15: Pago | P15: =Tabela2[[#This Row],[Total]]-Tabela2[[#This Row],[Valor]] -> -344.89886 | Q15: =Tabela2[[#This Row],[Valor parcela]]*Tabela2[[#This Row],[Parcelas faltantes]]-30 -> 40.185571
A16: 1 | B16: =VLOOKUP(Tabela2[[#This Row],[ID_Cliente]],Tabela5[#All],2,0) -> Armando rodrigues progenio neto | C16: 620 | D16: 45805 | E16: =SUM(Encargos!$A$5/12,Encargos!$C$5,Encargos!$E$5) -> 0.0325 | F16: {=Tabela1[Multa por atraso]} -> 0.01 | G16: 45805 | H16: 45814 | I16: 39 | J16: =IF(TODAY()-G16<0,"No prazo",IF(Tabela2[[#This Row],[Status]]="Pago",Tabela2[[#This Row],[Dia pagamento]]-Tabela2[[#This Row],[Vencimento]],TODAY()-G16)) -> 9 | K16: 2 | L16: 2 | M16: {=(C16+(C16*(E16*Tabela2[[#This Row],[Parcelas]]))+(C16*(Tabela1[I.O.F Diário]*Clientes!I16)))/K16+IF(TODAY()>G16,(C16*(F16*J16)),0)} -> 386.94138 | N16: =M16*K16 -> 773.88276 | O16: Pago | P16: =Tabela2[[#This Row],[Total]]-Tabela2[[#This Row],[Valor]] -> 153.88276 | Q16: =Tabela2[[#This Row],[Valor parcela]]*Tabela2[[#This Row],[Parcelas faltantes]] -> 773.88276
A17: 1 | B17: =VLOOKUP(Tabela2[[#This Row],[ID_Cliente]],Tabela5[#All],2,0) -> Armando rodrigues progenio neto | C17: 379.08 | D17: 45818 | E17: =SUM(Encargos!$A$5/12,Encargos!$C$5,Encargos!$E$5) -> 0.0325 | F17: {=Tabela1[Multa por atraso]} -> 0.01 | G17: 45875 | H17: 45842 | I17: 57 | J17: 57 | K17: 2 | L17: 2 | M17: {=(C17+(C17*(E17*Tabela2[[#This Row],[Parcelas]]))+(C17*(Tabela1[I.O.F Diário]*Clientes!I17)))/K17+IF(TODAY()>G17,(C17*(F17*J17)),0)} -> 418.82161 | N17: =M17*K17 -> 837.64322 | O17: Pago | P17: =Tabela2[[#This Row],[Total]]-Tabela2[[#This Row],[Valor]] -> 458.56322 | Q17: =Tabela2[[#This Row],[Valor parcela]]*Tabela2[[#This Row],[Parcelas faltantes]] -> 837.64322
A18: 1 | B18: =VLOOKUP(Tabela2[[#This Row],[ID_Cliente]],Tabela5[#All],2,0) -> Armando rodrigues progenio neto | C18: 472.93 | D18: 45842 | E18: =SUM(Encargos!$A$5/12,Encargos!$C$5,Encargos!$E$5) -> 0.0325 | F18: {=Tabela1[Multa por atraso]} -> 0.01 | G18: 45875 | H18: 45886 | I18: 30 | J18: =IF(TODAY()-G18<0,"No prazo",IF(Tabela2[[#This Row],[Status]]="Pago",Tabela2[[#This Row],[Dia pagamento]]-Tabela2[[#This Row],[Vencimento]],TODAY()-G18)) -> 11 | K18: 2 | L18: 2 | M18: {=(C18+(C18*(E18*Tabela2[[#This Row],[Parcelas]]))+(C18*(Tabela1[I.O.F Diário]*Clientes!I18)))/K18+IF(TODAY()>G18,(C18*(F18*J18)),0)} -> 304.43923 | N18: =M18*K18 -> 608.87846 | O18: Pago | P18: =Tabela2[[#This Row],[Total]]-Tabela2[[#This Row],[Valor]] -> 135.94846 | Q18: =Tabela2[[#This Row],[Valor parcela]]*Tabela2[[#This Row],[Parcelas faltantes]] -> 608.87846
A19: 1 | B19: =VLOOKUP(Tabela2[[#This Row],[ID_Cliente]],Tabela5[#All],2,0) -> Armando rodrigues progenio neto | C19: 1093 | D19: 45886 | E19: =SUM(Encargos!$A$5/12,Encargos!$C$5,Encargos!$E$5) -> 0.0325 | F19: {=Tabela1[Multa por atraso]} -> 0.01 | G19: 45997 | H19: 45936 | I19: 111 | J19: =IF(TODAY()-G19<0,"No prazo",IF(Tabela2[[#This Row],[Status]]="Pago",Tabela2[[#This Row],[Dia pagamento]]-Tabela2[[#This Row],[Vencimento]],TODAY()-G19)) -> -61 | K19: 4 | L19: 4 | M19: {=(C19+(C19*(E19*Tabela2[[#This Row],[Parcelas]]))+(C19*(Tabela1[I.O.F Diário]*Clientes!I19)))/K19+IF(TODAY()>G19,(C19*(F19*J19)),0)} -> -355.47038 | N19: =M19*K19 -> -1421.8815 | O19: Pago | P19: =Tabela2[[#This Row],[Total]]-Tabela2[[#This Row],[Valor]] -> -2514.8815 | Q19: =Tabela2[[#This Row],[Valor parcela]]*Tabela2[[#This Row],[Parcelas faltantes]] -> -1421.8815
A20: 1 | B20: =VLOOKUP(Tabela2[[#This Row],[ID_Cliente]],Tabela5[#All],2,0) -> Armando rodrigues progenio neto | C20: 1138 | D20: 45936 | E20: =SUM(Encargos!$A$5/12,Encargos!$C$5,Encargos!$E$5) -> 0.0325 | F20: {=Tabela1[Multa por atraso]} -> 0.01 | G20: 46148 | H20: 45997 | I20: 210 | J20: =IF(TODAY()-G20<0,"No prazo",IF(Tabela2[[#This Row],[Status]]="Pago",Tabela2[[#This Row],[Dia pagamento]]-Tabela2[[#This Row],[Vencimento]],TODAY()-G20)) -> No prazo | K20: 7 | L20: 6 | M20: {=(C20+(C20*(E20*Tabela2[[#This Row],[Parcelas]]))+(C20*(Tabela1[I.O.F Diário]*Clientes!I20)))/K20+IF(TODAY()>G20,(C20*(F20*J20)),0)} -> 202.35591 | N20: =M20*K20 -> 1416.4914 | O20: Pago | P20: =Tabela2[[#This Row],[Total]]-Tabela2[[#This Row],[Valor]] -> 278.49136 | Q20: =Tabela2[[#This Row],[Valor parcela]]*Tabela2[[#This Row],[Parcelas faltantes]] -> 1214.1355
A21: 1 | B21: =VLOOKUP(Tabela2[[#This Row],[ID_Cliente]],Tabela5[#All],2,0) -> Armando rodrigues progenio neto | C21: 1234.02 | D21: 45979 | E21: =SUM(Encargos!$A$5/12,Encargos!$C$5,Encargos!$E$5) -> 0.0325 | F21: {=Tabela1[Multa por atraso]} -> 0.01 | G21: 46179 | H21: 46024 | I21: 182 | J21: =IF(TODAY()-G21<0,"No prazo",IF(Tabela2[[#This Row],[Status]]="Pago",Tabela2[[#This Row],[Dia pagamento]]-Tabela2[[#This Row],[Vencimento]],TODAY()-G21)) -> No prazo | K21: 6 | L21: 6 | M21: {=(C21+(C21*(E21*Tabela2[[#This Row],[Parcelas]]))+(C21*(Tabela1[I.O.F Diário]*Clientes!I21)))/K21+IF(TODAY()>G21,(C21*(F21*J21)),0)} -> 248.84507 | N21: =M21*K21 -> 1493.0704 | O21: Pago | P21: =Tabela2[[#This Row],[Total]]-Tabela2[[#This Row],[Valor]] -> 259.05041 | Q21: =Tabela2[[#This Row],[Valor parcela]]*Tabela2[[#This Row],[Parcelas faltantes]] -> 1493.0704
A22: 1 | B22: =VLOOKUP(Tabela2[[#This Row],[ID_Cliente]],Tabela5[#All],2,0) -> Armando rodrigues progenio neto | C22: 1852.5422 | D22: 45659 | E22: =SUM(Encargos!$A$5/12,Encargos!$C$5,Encargos!$E$5) -> 0.0325 | F22: {=Tabela1[Multa por atraso]} -> 0.01 | G22: 46179 | H22: 45665 | I22: 210 | J22: =IF(TODAY()-G22<0,"No prazo",IF(Tabela2[[#This Row],[Status]]="Pago",Tabela2[[#This Row],[Dia pagamento]]-Tabela2[[#This Row],[Vencimento]],TODAY()-G22)) -> No prazo | K22: 7 | L22: 0 | M22: {=(C22+(C22*(E22*Tabela2[[#This Row],[Parcelas]]))+(C22*(Tabela1[I.O.F Diário]*Clientes!I22)))/K22+IF(TODAY()>G22,(C22*(F22*J22)),0)} -> 329.41375 | N22: =M22*K22 -> 2305.8963 | O22: Pago | P22: =Tabela2[[#This Row],[Total]]-Tabela2[[#This Row],[Valor]] -> 453.35412 | Q22: =Tabela2[[#This Row],[Valor parcela]]*Tabela2[[#This Row],[Parcelas faltantes]] -> 0
A23: 1 | B23: =VLOOKUP(Tabela2[[#This Row],[ID_Cliente]],Tabela5[#All],2,0) -> Armando rodrigues progenio neto | C23: =2305.9+170 -> 2475.9 | D23: 45665 | E23: =SUM(Encargos!$A$5/12,Encargos!$C$5,Encargos!$E$5) -> 0.0325 | F23: {=Tabela1[Multa por atraso]} -> 0.01 | G23: 46271 | H23: 45675 | I23: 241 | J23: =IF(TODAY()-G23<0,"No prazo",IF(Tabela2[[#This Row],[Status]]="Pago",Tabela2[[#This Row],[Dia pagamento]]-Tabela2[[#This Row],[Vencimento]],TODAY()-G23)) -> No prazo | K23: 8 | L23: 7 | M23: {=(C23+(C23*(E23*Tabela2[[#This Row],[Parcelas]]))+(C23*(Tabela1[I.O.F Diário]*Clientes!I23)))/K23+IF(TODAY()>G23,(C23*(F23*J23)),0)} -> 396.07034 | N23: =M23*K23 -> 3168.5627 | O23: Pago | P23: =Tabela2[[#This Row],[Total]]-Tabela2[[#This Row],[Valor]] -> 692.66274 | Q23: =Tabela2[[#This Row],[Valor parcela]]*Tabela2[[#This Row],[Parcelas faltantes]] -> 2772.4924
A24: 1 | B24: =VLOOKUP(Tabela2[[#This Row],[ID_Cliente]],Tabela5[#All],2,0) -> Armando rodrigues progenio neto | C24: 2772.49 | D24: 46040 | E24: =SUM(Encargos!$A$5/12,Encargos!$C$5,Encargos!$E$5) -> 0.0325 | F24: {=Tabela1[Multa por atraso]} -> 0.01 | G24: 46332 | H24: 46048 | I24: 292 | J24: =IF(TODAY()-G24<0,"No prazo",IF(Tabela2[[#This Row],[Status]]="Pago",Tabela2[[#This Row],[Dia pagamento]]-Tabela2[[#This Row],[Vencimento]],TODAY()-G24)) -> No prazo | K24: 10 | L24: 10 | M24: {=(C24+(C24*(E24*Tabela2[[#This Row],[Parcelas]]))+(C24*(Tabela1[I.O.F Diário]*Clientes!I24)))/K24+IF(TODAY()>G24,(C24*(F24*J24)),0)} -> 373.99338 | N24: =M24*K24 -> 3739.9338 | O24: Pago | P24: =Tabela2[[#This Row],[Total]]-Tabela2[[#This Row],[Valor]] -> 967.44375 | Q24: =Tabela2[[#This Row],[Valor parcela]]*Tabela2[[#This Row],[Parcelas faltantes]] -> 3739.9338
A25: 2 | B25: Waldriano progenio monteiro | C25: 100 | D25: 46046 | E25: 0.0325 | F25: 0.01 | G25: 46077 | H25: 46079 | I25: =Tabela2[[#This Row],[Vencimento]]-TODAY() -> -11 | J25: =IF(TODAY()-G25<0,"No prazo",IF(Tabela2[[#This Row],[Status]]="Pago",Tabela2[[#This Row],[Dia pagamento]]-Tabela2[[#This Row],[Vencimento]],TODAY()-G25)) -> 2 | K25: 1 | L25: 1 | M25: {=(C25+(C25*(E25*Tabela2[[#This Row],[Parcelas]]))+(C25*(Tabela1[I.O.F Diário]*Clientes!I25)))/K25+IF(TODAY()>G25,(C25*(F25*J25)),0)} -> 105.1598 | N25: =M25*K25 -> 105.1598 | O25: Pago | P25: =Tabela2[[#This Row],[Total]]-Tabela2[[#This Row],[Valor]] -> 5.1598 | Q25: =Tabela2[[#This Row],[Valor parcela]]*Tabela2[[#This Row],[Parcelas faltantes]] -> 105.1598 | R25: =Q22 -> 0
A26: 1 | B26: =VLOOKUP(Tabela2[[#This Row],[ID_Cliente]],Tabela5[#All],2,0) -> Armando rodrigues progenio neto | C26: =3739.93+500 -> 4239.93 | D26: 46048 | E26: =SUM(Encargos!$A$5/12,Encargos!$C$5,Encargos!$E$5) -> 0.0325 | F26: {=Tabela1[Multa por atraso]} -> 0.01 | G26: 46366 | H26: 46051 | I26: 318 | J26: =IF(TODAY()-G26<0,"No prazo",IF(Tabela2[[#This Row],[Status]]="Pago",Tabela2[[#This Row],[Dia pagamento]]-Tabela2[[#This Row],[Vencimento]],TODAY()-G26)) -> No prazo | K26: 11 | L26: 11 | M26: {=(C26+(C26*(E26*Tabela2[[#This Row],[Parcelas]]))+(C26*(Tabela1[I.O.F Diário]*Clientes!I26)))/K26+IF(TODAY()>G26,(C26*(F26*J26)),0)} -> 533.29685 | N26: =M26*K26 -> 5866.2654 | O26: Renegociado | P26: =Tabela2[[#This Row],[Total]]-Tabela2[[#This Row],[Valor]] -> 1626.3354 | Q26: =Tabela2[[#This Row],[Valor parcela]]*Tabela2[[#This Row],[Parcelas faltantes]] -> 5866.2654 | R26: =Q26*R25/Q25 -> 0
A27: 1 | B27: =VLOOKUP(Tabela2[[#This Row],[ID_Cliente]],Tabela5[#All],2,0) -> Armando rodrigues progenio neto | C27: =5866+1700 -> 7566 | D27: 46051 | E27: =SUM(Encargos!$A$5/12,Encargos!$C$5,Encargos!$E$5) -> 0.0325 | F27: {=Tabela1[Multa por atraso]} -> 0.01 | G27: 46544 | H27: 46061 | I27: 493 | J27: =IF(TODAY()-G27<0,"No prazo",IF(Tabela2[[#This Row],[Status]]="Pago",Tabela2[[#This Row],[Dia pagamento]]-Tabela2[[#This Row],[Vencimento]],TODAY()-G27)) -> No prazo | K27: 18 | L27: 17 | M27: {=(C27+(C27*(E27*Tabela2[[#This Row],[Parcelas]]))+(C27*(Tabela1[I.O.F Diário]*Clientes!I27)))/K27+IF(TODAY()>G27,(C27*(F27*J27)),0)} -> 683.22073 | N27: =M27*K27 -> 12297.973 | O27: Renegociado | P27: =Tabela2[[#This Row],[Total]]-Tabela2[[#This Row],[Valor]] -> 4731.9731 | Q27: =Tabela2[[#This Row],[Valor parcela]]*Tabela2[[#This Row],[Parcelas faltantes]] -> 11614.752
A28: 1 | B28: Armando rodrigues progenio neto | C28: =Q27+200 -> 11814.752 | D28: 46061 | E28: =SUM(Encargos!$A$5/12,Encargos!$C$5,Encargos!$E$5) -> 0.0325 | F28: {=Tabela1[Multa por atraso]} -> 0.01 | G28: 46791 | I28: =Tabela2[[#This Row],[Vencimento]]-Tabela2[[#This Row],[Data]] -> 730 | J28: =IF(TODAY()-G28<0,"No prazo",IF(Tabela2[[#This Row],[Status]]="Pago",Tabela2[[#This Row],[Dia pagamento]]-Tabela2[[#This Row],[Vencimento]],TODAY()-G28)) -> No prazo | K28: 24 | L28: 23 | M28: {=(C28+(C28*(E28*Tabela2[[#This Row],[Parcelas]]))+(C28*(Tabela1[I.O.F Diário]*Clientes!I28)))/K28+IF(TODAY()>G28,(C28*(F28*J28)),0)} -> 905.72876 | N28: =M28*K28 -> 21737.49 | O28: À pagar | P28: =Tabela2[[#This Row],[Total]]-Tabela2[[#This Row],[Valor]] -> 9922.7379 | Q28: =Tabela2[[#This Row],[Valor parcela]]*Tabela2[[#This Row],[Parcelas faltantes]] -> 20831.762
Q32: =Q28 -> 20831.762

Sheet Base Clientes
K1: Endereços
A3: ID_Cliente | B3: Nome | C3: CPF | D3: Contato 1 | E3: Contato 2 | F3: Email | G3: id_endereço | K3: Id_endereço | L3: ID_Cliente | M3: Cep | N3: Estado | O3: Cidade | P3: Bairro | Q3: Rua | R3: Casa
A4: 1 | B4: Armando rodrigues progenio neto | C4: 06361784207 | D4: (91)98846-8119 | E4: - | F4: rodriguesarmando225@gmail.com | G4: 1 | K4: 1 | L4: 1 | M4: 35501520 | N4: MG | O4: Divinópolis | P4: Jardim das acácias | Q4: Jacatiá | R4: 81

Sheet Encargos
A1: Encargos
A4: I.P.C.A | B4: Multa por atraso | C4: I.O.F Fixo | D4: I.O.F Diário | E4: Taxa administrativa
A5: 0.15 | B5: 0.01 | C5: 0.01 | D5: 8.2e-05 | E5: 0.01

Sheet Financeiro
A3: Saldo a receber
A4: =SUMIF(Tabela2[Status],"À Pagar",Tabela2[Valor Faltante]) -> 20831.762
